{
  "hash": "c80a30bc",
  "configHash": "6fddcfbe",
  "lockfileHash": "e3cc3069",
  "browserHash": "4ccb034a",
  "optimized": {
    "alpinejs": {
      "src": "../../node_modules/alpinejs/dist/module.esm.js",
      "file": "alpinejs.js",
      "fileHash": "5c1ba842",
      "needsInterop": false
    },
    "axios": {
      "src": "../../node_modules/axios/index.js",
      "file": "axios.js",
      "fileHash": "9c31d05f",
      "needsInterop": false
    }
  },
  "chunks": {
    "chunk-PZ5AY32C": {
      "file": "chunk-PZ5AY32C.js"
    }
  }
}